{
    "locale": "zh-CN",
    "has_enough_context": false,
    "thought": "用户要求预测未来6个月（从6月到11月）的销量。为了提供准确的预测，需要收集全面的市场数据，包括历史销售数据、当前市场状态、未来市场指标、相关方分析、定量和定性市场数据、比较分析、市场风险评估以及价格分析。",
    "title": "吉利银河E5未来6个月销量预测",
    "steps": [
        {
            "need_web_search": false,
            "title": "加载本地数据",
            "description": "从本地文件路径加载有关吉利银河E5的历史销售数据和其他相关信息。",
            "step_type": "loading"
        },
        {
            "need_web_search": true,
            "title": "收集销售价格数据",
            "description": "收集吉利银河E5的价格趋势、竞争定价、价格-性能比以及价格对市场需求的影响等详细信息。",
            "step_type": "research"
        },
        {
            "need_web_search": true,
            "title": "分析市场历史数据",
            "description": "收集吉利银河E5过去几年的销售数据，包括月度和季度销售量，以及市场事件的时间线。",
            "step_type": "research"
        },
        {
            "need_web_search": true,
            "title": "评估当前市场状态",
            "description": "收集当前市场指标，包括市场份额、竞争对手表现、最新市场发展、定价趋势和销售价格分布。",
            "step_type": "research"
        },
        {
            "need_web_search": false,
            "title": "开发销售预测模型",
            "description": "使用收集到的数据开发销售预测模型，进行模型训练和测试，评估模型性能并生成初步的销售预测。",
            "step_type": "processing"
        },
        {
            "need_web_search": false,
            "title": "最终销量预测",
            "description": "基于模型的初步预测，结合所有收集到的市场信息和洞察，调整预测结果，生成最终的销量预测报告，并提供置信区间。",
            "step_type": "prediction"
        }
    ]
}